PyMake/__init__.py
PyMake/__version__.py
PyMake/console/__init__.py
PyMake/console/builder/__init__.py
PyMake/console/builder/abc_builder.py
PyMake/console/builder/builder.py
PyMake/console/builder/cmd_builder.py
PyMake/console/builder/env_builder.py
PyMake/console/builder/var_builder.py
PyMake/console/helpers.py
PyMake/console/inspect.py
PyMake/console/list.py
PyMake/console/parser/__init__.py
PyMake/console/parser/parser.py
PyMake/console/run.py
PyMake/decorators.py
PyMake/exceptions.py
PyMake/main.py
pythonmake-0.0.16.dist-info/LICENSE
pythonmake-0.0.16.dist-info/METADATA
pythonmake-0.0.16.dist-info/WHEEL
pythonmake-0.0.16.dist-info/entry_points.txt
pythonmake-0.0.16.dist-info/RECORD
