Metadata-Version: 2.1
Name: PythonMake
Version: 0.0.16
Summary: A simple CLI wrapper
Home-page: https://github.com/haryle/PyMake
License: MIT
Keywords: cli,commands
Author: hoangson
Author-email: lehoangsonsg@gmail.com
Requires-Python: >=3.10
Classifier: Development Status :: 2 - Pre-Alpha
Classifier: Environment :: Console
Classifier: Intended Audience :: Developers
Classifier: Intended Audience :: Information Technology
Classifier: Intended Audience :: System Administrators
Classifier: License :: OSI Approved :: MIT License
Classifier: Operating System :: Unix
Classifier: Programming Language :: Python :: 3
Classifier: Programming Language :: Python :: 3.10
Classifier: Programming Language :: Python :: 3.11
Classifier: Topic :: Software Development
Classifier: Topic :: Software Development :: Libraries
Classifier: Topic :: Software Development :: Libraries :: Application Frameworks
Classifier: Topic :: Software Development :: Libraries :: Python Modules
Requires-Dist: PyYAML (>=6.0.1,<7.0.0)
Requires-Dist: paramiko (>=3.3.1,<4.0.0)
Requires-Dist: pydantic (>=2.3.0,<3.0.0)
Project-URL: Repository, https://github.com/haryle/PyMake
